{
  "programId": "BHRM",
  "programName": "Honours Bachelor of Commerce – Human Resources Management",
  "semesters": [
    {
      "id": "semester1",
      "name": "Semester 1",
      "courses": [
        {
          "id": "bab100",
          "code": "BAB100",
          "name": "Introduction to Canadian Business"
        },
        {
          "id": "bab110",
          "code": "BAB110",
          "name": "Financial Mathematics"
        },
        {
          "id": "bab120",
          "code": "BAB120",
          "name": "Computer Applications for Business I"
        },
        {
          "id": "bab140",
          "code": "BAB140",
          "name": "Introduction to Financial Accounting"
        },
        {
          "id": "bba101",
          "code": "BBA101",
          "name": "Business Presentations Strategy"
        },
        {
          "id": "eng106",
          "code": "ENG106",
          "name": "Writing Strategies"
        }
      ]
    },
    {
      "id": "semester2",
      "name": "Semester 2",
      "courses": [
        {
          "id": "bab210",
          "code": "BAB210",
          "name": "Business Statistics"
        },
        {
          "id": "bab220",
          "code": "BAB220",
          "name": "Computer Applications for Business II"
        },
        {
          "id": "bab231",
          "code": "BAB231",
          "name": "Introduction to Business Law"
        },
        {
          "id": "bab240",
          "code": "BAB240",
          "name": "Management Accounting"
        },
        {
          "id": "eng205",
          "code": "ENG205",
          "name": "Applied Communication for Business and Industry"
        },
        {
          "id": "hrm701",
          "code": "HRM701",
          "name": "Introduction to Human Resources Management"
        }
      ]
    },
    {
      "id": "semester3",
      "name": "Semester 3",
      "courses": [
        {
          "id": "bab235",
          "code": "BAB235",
          "name": "Introduction to Marketing"
        },
        {
          "id": "hst310",
          "code": "HST310",
          "name": "Business Ethics"
        },
        {
          "id": "hst330",
          "code": "HST330",
          "name": "Business Finance"
        },
        {
          "id": "hst430",
          "code": "HST430",
          "name": "Organizational Behaviour"
        },
        {
          "id": "lsp240",
          "code": "LSP240",
          "name": "Micro Economics - Theory and Practice"
        }
      ],
      "requirements": [
        {
          "type": "Liberal Studies Course",
          "count": 1,
          "description": "Liberal Studies Course (1)"
        }
      ],
      "totalCourses": 6
    },
    {
      "id": "semester4",
      "name": "Semester 4",
      "courses": [
        {
          "id": "bab905",
          "code": "BAB905",
          "name": "Project Management"
        },
        {
          "id": "inx117",
          "code": "INX117",
          "name": "Foundations of Global Sustainability"
        },
        {
          "id": "lsp101",
          "code": "LSP101",
          "name": "World Geography"
        },
        {
          "id": "lsp340",
          "code": "LSP340",
          "name": "Macroeconomics - Theory and Practice"
        },
        {
          "id": "mrt296",
          "code": "MRT296",
          "name": "Integrated Marketing Communications"
        },
        {
          "id": "wtp200",
          "code": "WTP200",
          "name": "Work Term Preparation"
        }
      ]
    },
    {
      "id": "semester5",
      "name": "Semester 4",
      "courses": [
        {
          "id": "hst771",
          "code": "HST771",
          "name": "Human Resource Strategy and Technology, Co-op"
        }
      ]
    },
    {
      "id": "semester6",
      "name": "Semester 5",
      "courses": [
        {
          "id": "bmt850",
          "code": "BMT850",
          "name": "Strategic Management"
        },
        {
          "id": "gcn500",
          "code": "GCN500",
          "name": "Consultative Skills in a Global Environment"
        },
        {
          "id": "hrm782",
          "code": "HRM782",
          "name": "Recruitment and Selection Techniques"
        },
        {
          "id": "hrm848",
          "code": "HRM848",
          "name": "Training Techniques and Practices"
        },
        {
          "id": "hst400",
          "code": "HST400",
          "name": "Operations Management"
        },
        {
          "id": "hst540",
          "code": "HST540",
          "name": "Compensation"
        }
      ]
    },
    {
      "id": "semester7",
      "name": "Semester 6",
      "courses": [
        {
          "id": "bmt700",
          "code": "BMT700",
          "name": "International Business Management"
        },
        {
          "id": "hst620",
          "code": "HST620",
          "name": "Human Resources Research and Information Systems"
        },
        {
          "id": "hst720",
          "code": "HST720",
          "name": "Occupational Health and Safety"
        },
        {
          "id": "hst750",
          "code": "HST750",
          "name": "Industrial Relations"
        }
      ],
      "requirements": [
        {
          "type": "Liberal Studies Course",
          "count": 1,
          "description": "Liberal Studies Course (1)"
        }
      ],
      "totalCourses": 5
    },
    {
      "id": "semester8",
      "name": "Semester 7",
      "courses": [
        {
          "id": "hst520",
          "code": "HST520",
          "name": "Employment Law"
        },
        {
          "id": "hst610",
          "code": "HST610",
          "name": "Pensions and Benefits"
        },
        {
          "id": "hst850",
          "code": "HST850",
          "name": "Human Resource Planning"
        },
        {
          "id": "hst860",
          "code": "HST860",
          "name": "Technology Enhanced Learning"
        },
        {
          "id": "lsp700",
          "code": "LSP700",
          "name": "Applied Research Methodology"
        }
      ]
    },
    {
      "id": "semester9",
      "name": "Semester 8",
      "courses": [
        {
          "id": "hst810",
          "code": "HST810",
          "name": "Advanced Issues in Organizational Development"
        },
        {
          "id": "hst840",
          "code": "HST840",
          "name": "Multidisciplinary Business Case"
        },
        {
          "id": "hst870",
          "code": "HST870",
          "name": "Advanced Applications in HRIS"
        }
      ],
      "requirements": [
        {
          "type": "Liberal Studies Course",
          "count": 1,
          "description": "Liberal Studies Course (1)"
        }
      ],
      "totalCourses": 4
    }
  ]
}
